.gitignore
LICENSE
README.md
pyproject.toml
setup.py
.github/workflows/build_and_publish_to_pypi.yml
openspeechtointent/__init__.py
openspeechtointent/forced_alignment.cpp
openspeechtointent/model.py
openspeechtointent/utils.py
openspeechtointent.egg-info/PKG-INFO
openspeechtointent.egg-info/SOURCES.txt
openspeechtointent.egg-info/dependency_links.txt
openspeechtointent.egg-info/requires.txt
openspeechtointent.egg-info/top_level.txt
openspeechtointent/resources/models/citrinet_spectrogram_filterbank.npy
openspeechtointent/resources/models/citrinet_tokenizer.pkl
openspeechtointent/resources/models/citrinet_vocab.json
test/intents/test_intents.json
test/resources/sample_1.wav