Metadata-Version: 2.1
Name: openspeechtointent
Version: 0.1.0
Summary: A simple, but performant framework for mapping speech directly to categories and intents.
Author-email: David Scripka <david.scripka@gmail.com>
License:                                  Apache License
Project-URL: Homepage, https://github.com/dscripka/openspeechtointent
Classifier: Development Status :: 3 - Alpha
Classifier: Intended Audience :: Developers
Classifier: License :: OSI Approved :: Apache Software License
Classifier: Operating System :: OS Independent
Classifier: Programming Language :: Python :: 3
Classifier: Programming Language :: Python :: 3.8
Classifier: Programming Language :: Python :: 3.9
Classifier: Programming Language :: Python :: 3.10
Requires-Python: >=3.8
License-File: LICENSE
Requires-Dist: numpy
Requires-Dist: onnxruntime
Requires-Dist: sentencepiece>=0.2.0
